realtime_vad/__init__.py
realtime_vad/audio_cache.py
realtime_vad/detector.py
realtime_vad/utils.py
realtime_vad/files/silero_vad.jit
realtime_vad_python-0.1.1.dist-info/licenses/LICENSE
realtime_vad_python-0.1.1.dist-info/METADATA
realtime_vad_python-0.1.1.dist-info/WHEEL
realtime_vad_python-0.1.1.dist-info/top_level.txt
realtime_vad_python-0.1.1.dist-info/RECORD
