Metadata-Version: 2.4
Name: realtime-vad-python
Version: 0.1.1
Summary: Python实时VAD检测库，基于Silero VAD模型
Home-page: https://github.com/mereithhh/realtime-vad-python
Author: Mereith
Author-email: wanglu@mereith.com
Classifier: Development Status :: 3 - Alpha
Classifier: Intended Audience :: Developers
Classifier: License :: OSI Approved :: MIT License
Classifier: Programming Language :: Python :: 3
Classifier: Programming Language :: Python :: 3.7
Classifier: Programming Language :: Python :: 3.8
Classifier: Programming Language :: Python :: 3.9
Classifier: Programming Language :: Python :: 3.10
Classifier: Topic :: Multimedia :: Sound/Audio :: Speech
Classifier: Topic :: Scientific/Engineering :: Artificial Intelligence
Requires-Python: >=3.7
License-File: LICENSE
Requires-Dist: numpy
Requires-Dist: torch>=1.13.0
Requires-Dist: torchaudio>=0.13.0
Provides-Extra: dev
Requires-Dist: pytest; extra == "dev"
Requires-Dist: black; extra == "dev"
Requires-Dist: isort; extra == "dev"
Requires-Dist: flake8; extra == "dev"
Requires-Dist: build; extra == "dev"
Requires-Dist: twine; extra == "dev"
Provides-Extra: examples
Requires-Dist: pyaudio; extra == "examples"
Dynamic: author
Dynamic: author-email
Dynamic: classifier
Dynamic: description
Dynamic: description-content-type
Dynamic: home-page
Dynamic: license-file
Dynamic: provides-extra
Dynamic: requires-dist
Dynamic: requires-python
Dynamic: summary
